{
  "timestamp": "2025-09-19T06:35:42.459398",
  "last_updated": "2025-09-19 06:35:42 UTC",
  "data_sources": [
    "Shodan Pro",
    "GreyNoise",
    "VirusTotal"
  ],
  "countries": {
    "US": {
      "exposed_services": 40610903,
      "critical_vulns": 812218,
      "threat_activity": 1081
    },
    "CN": {
      "exposed_services": 10611294,
      "critical_vulns": 212225,
      "threat_activity": 2057
    },
    "DE": {
      "exposed_services": 9678618,
      "critical_vulns": 193572,
      "threat_activity": 1244
    },
    "JP": {
      "exposed_services": 4880196,
      "critical_vulns": 97603,
      "threat_activity": 1465
    },
    "HK": {
      "exposed_services": 4225817,
      "critical_vulns": 84516,
      "threat_activity": 0
    },
    "GB": {
      "exposed_services": 3703077,
      "critical_vulns": 74061,
      "threat_activity": 2270
    },
    "IN": {
      "exposed_services": 3475206,
      "critical_vulns": 69504,
      "threat_activity": 0
    },
    "NL": {
      "exposed_services": 3337688,
      "critical_vulns": 66753,
      "threat_activity": 0
    },
    "SG": {
      "exposed_services": 3303068,
      "critical_vulns": 66061,
      "threat_activity": 0
    },
    "FR": {
      "exposed_services": 3301794,
      "critical_vulns": 66035,
      "threat_activity": 1020
    },
    "RU": {
      "exposed_services": 2853974,
      "critical_vulns": 57079,
      "threat_activity": 946
    },
    "BR": {
      "exposed_services": 2469346,
      "critical_vulns": 49386,
      "threat_activity": 0
    },
    "KR": {
      "exposed_services": 2423378,
      "critical_vulns": 48467,
      "threat_activity": 1372
    },
    "CA": {
      "exposed_services": 2213381,
      "critical_vulns": 44267,
      "threat_activity": 1509
    },
    "AU": {
      "exposed_services": 1931397,
      "critical_vulns": 38627,
      "threat_activity": 2013
    },
    "IT": {
      "exposed_services": 1760259,
      "critical_vulns": 35205,
      "threat_activity": 0
    },
    "IE": {
      "exposed_services": 1712693,
      "critical_vulns": 34253,
      "threat_activity": 0
    },
    "TW": {
      "exposed_services": 1398944,
      "critical_vulns": 27978,
      "threat_activity": 0
    },
    "VN": {
      "exposed_services": 1192855,
      "critical_vulns": 23857,
      "threat_activity": 0
    },
    "ES": {
      "exposed_services": 1050180,
      "critical_vulns": 21003,
      "threat_activity": 0
    },
    "PL": {
      "exposed_services": 967235,
      "critical_vulns": 19344,
      "threat_activity": 0
    },
    "SE": {
      "exposed_services": 951798,
      "critical_vulns": 19035,
      "threat_activity": 0
    },
    "FI": {
      "exposed_services": 907402,
      "critical_vulns": 18148,
      "threat_activity": 0
    },
    "ID": {
      "exposed_services": 884027,
      "critical_vulns": 17680,
      "threat_activity": 0
    },
    "MX": {
      "exposed_services": 856340,
      "critical_vulns": 17126,
      "threat_activity": 0
    },
    "TH": {
      "exposed_services": 761376,
      "critical_vulns": 15227,
      "threat_activity": 0
    },
    "VE": {
      "exposed_services": 689512,
      "critical_vulns": 13790,
      "threat_activity": 0
    },
    "TR": {
      "exposed_services": 679174,
      "critical_vulns": 13583,
      "threat_activity": 0
    },
    "CH": {
      "exposed_services": 639167,
      "critical_vulns": 12783,
      "threat_activity": 0
    },
    "AR": {
      "exposed_services": 635741,
      "critical_vulns": 12714,
      "threat_activity": 0
    },
    "ZA": {
      "exposed_services": 604521,
      "critical_vulns": 12090,
      "threat_activity": 0
    },
    "BE": {
      "exposed_services": 553283,
      "critical_vulns": 11065,
      "threat_activity": 0
    },
    "RO": {
      "exposed_services": 517957,
      "critical_vulns": 10359,
      "threat_activity": 0
    },
    "AT": {
      "exposed_services": 482727,
      "critical_vulns": 9654,
      "threat_activity": 0
    },
    "IR": {
      "exposed_services": 443297,
      "critical_vulns": 8865,
      "threat_activity": 0
    },
    "MY": {
      "exposed_services": 425224,
      "critical_vulns": 8504,
      "threat_activity": 0
    },
    "IL": {
      "exposed_services": 409366,
      "critical_vulns": 8187,
      "threat_activity": 0
    },
    "CZ": {
      "exposed_services": 400661,
      "critical_vulns": 8013,
      "threat_activity": 0
    },
    "UA": {
      "exposed_services": 377370,
      "critical_vulns": 7547,
      "threat_activity": 0
    },
    "TN": {
      "exposed_services": 360477,
      "critical_vulns": 7209,
      "threat_activity": 0
    },
    "CO": {
      "exposed_services": 356282,
      "critical_vulns": 7125,
      "threat_activity": 0
    },
    "CL": {
      "exposed_services": 345521,
      "critical_vulns": 6910,
      "threat_activity": 0
    },
    "KZ": {
      "exposed_services": 303589,
      "critical_vulns": 6071,
      "threat_activity": 0
    },
    "AE": {
      "exposed_services": 298883,
      "critical_vulns": 5977,
      "threat_activity": 0
    },
    "DO": {
      "exposed_services": 294770,
      "critical_vulns": 5895,
      "threat_activity": 0
    },
    "PH": {
      "exposed_services": 289221,
      "critical_vulns": 5784,
      "threat_activity": 0
    },
    "BG": {
      "exposed_services": 286070,
      "critical_vulns": 5721,
      "threat_activity": 0
    },
    "EG": {
      "exposed_services": 252571,
      "critical_vulns": 5051,
      "threat_activity": 0
    },
    "DK": {
      "exposed_services": 245862,
      "critical_vulns": 4917,
      "threat_activity": 0
    },
    "HU": {
      "exposed_services": 235882,
      "critical_vulns": 4717,
      "threat_activity": 0
    }
  },
  "organizations": {
    "Amazon": {
      "exposed_services": 18061539,
      "critical_vulns": 270923
    },
    "Google": {
      "exposed_services": 573159116,
      "critical_vulns": 8597386
    },
    "Microsoft": {
      "exposed_services": 7156656,
      "critical_vulns": 107349
    },
    "Cloudflare": {
      "exposed_services": 8058090,
      "critical_vulns": 120871
    },
    "DigitalOcean": {
      "exposed_services": 7794617,
      "critical_vulns": 116919
    }
  },
  "global_stats": {
    "total_exposed_services": 121589374,
    "total_critical_vulns": 2431761,
    "total_threat_activity": 14977,
    "malicious_domains": 0,
    "suspicious_domains": 0
  },
  "api_status": {
    "shodan": "active",
    "greynoise": "active",
    "virustotal": "active"
  }
}