{
  "timestamp": "2026-04-20T08:01:39.333250",
  "last_updated": "2026-04-20 08:01:39 UTC",
  "data_sources": [
    "Shodan Pro",
    "GreyNoise",
    "VirusTotal"
  ],
  "countries": {
    "US": {
      "exposed_services": 40667323,
      "critical_vulns_estimate": 813346,
      "threat_activity": 1185
    },
    "DE": {
      "exposed_services": 9788223,
      "critical_vulns_estimate": 195764,
      "threat_activity": 1745
    },
    "CN": {
      "exposed_services": 9732292,
      "critical_vulns_estimate": 194645,
      "threat_activity": 1296
    },
    "JP": {
      "exposed_services": 4975865,
      "critical_vulns_estimate": 99517,
      "threat_activity": 1907
    },
    "HK": {
      "exposed_services": 4030663,
      "critical_vulns_estimate": 80613,
      "threat_activity": 0
    },
    "GB": {
      "exposed_services": 3820027,
      "critical_vulns_estimate": 76400,
      "threat_activity": 2235
    },
    "SG": {
      "exposed_services": 3525305,
      "critical_vulns_estimate": 70506,
      "threat_activity": 0
    },
    "IN": {
      "exposed_services": 3429298,
      "critical_vulns_estimate": 68585,
      "threat_activity": 0
    },
    "FR": {
      "exposed_services": 3315258,
      "critical_vulns_estimate": 66305,
      "threat_activity": 1288
    },
    "NL": {
      "exposed_services": 3133136,
      "critical_vulns_estimate": 62662,
      "threat_activity": 0
    },
    "BR": {
      "exposed_services": 2437009,
      "critical_vulns_estimate": 48740,
      "threat_activity": 0
    },
    "KR": {
      "exposed_services": 2400551,
      "critical_vulns_estimate": 48011,
      "threat_activity": 1506
    },
    "IE": {
      "exposed_services": 2166078,
      "critical_vulns_estimate": 43321,
      "threat_activity": 0
    },
    "CA": {
      "exposed_services": 2141807,
      "critical_vulns_estimate": 42836,
      "threat_activity": 1044
    },
    "AU": {
      "exposed_services": 2049968,
      "critical_vulns_estimate": 40999,
      "threat_activity": 2326
    },
    "IT": {
      "exposed_services": 1606328,
      "critical_vulns_estimate": 32126,
      "threat_activity": 0
    },
    "TW": {
      "exposed_services": 1301848,
      "critical_vulns_estimate": 26036,
      "threat_activity": 0
    },
    "VN": {
      "exposed_services": 1120247,
      "critical_vulns_estimate": 22404,
      "threat_activity": 0
    },
    "ES": {
      "exposed_services": 1056768,
      "critical_vulns_estimate": 21135,
      "threat_activity": 0
    },
    "FI": {
      "exposed_services": 1016535,
      "critical_vulns_estimate": 20330,
      "threat_activity": 0
    },
    "SE": {
      "exposed_services": 1012425,
      "critical_vulns_estimate": 20248,
      "threat_activity": 0
    },
    "RU": {
      "exposed_services": 970207,
      "critical_vulns_estimate": 19404,
      "threat_activity": 976
    },
    "PL": {
      "exposed_services": 903553,
      "critical_vulns_estimate": 18071,
      "threat_activity": 0
    },
    "ID": {
      "exposed_services": 851536,
      "critical_vulns_estimate": 17030,
      "threat_activity": 0
    },
    "MX": {
      "exposed_services": 782218,
      "critical_vulns_estimate": 15644,
      "threat_activity": 0
    },
    "TH": {
      "exposed_services": 695303,
      "critical_vulns_estimate": 13906,
      "threat_activity": 0
    },
    "CH": {
      "exposed_services": 658660,
      "critical_vulns_estimate": 13173,
      "threat_activity": 0
    },
    "TR": {
      "exposed_services": 639884,
      "critical_vulns_estimate": 12797,
      "threat_activity": 0
    },
    "ZA": {
      "exposed_services": 613602,
      "critical_vulns_estimate": 12272,
      "threat_activity": 0
    },
    "AR": {
      "exposed_services": 525864,
      "critical_vulns_estimate": 10517,
      "threat_activity": 0
    },
    "BE": {
      "exposed_services": 516147,
      "critical_vulns_estimate": 10322,
      "threat_activity": 0
    },
    "AE": {
      "exposed_services": 514382,
      "critical_vulns_estimate": 10287,
      "threat_activity": 0
    },
    "VE": {
      "exposed_services": 507614,
      "critical_vulns_estimate": 10152,
      "threat_activity": 0
    },
    "RO": {
      "exposed_services": 492909,
      "critical_vulns_estimate": 9858,
      "threat_activity": 0
    },
    "AT": {
      "exposed_services": 459634,
      "critical_vulns_estimate": 9192,
      "threat_activity": 0
    },
    "MY": {
      "exposed_services": 424422,
      "critical_vulns_estimate": 8488,
      "threat_activity": 0
    },
    "CZ": {
      "exposed_services": 412057,
      "critical_vulns_estimate": 8241,
      "threat_activity": 0
    },
    "IL": {
      "exposed_services": 407132,
      "critical_vulns_estimate": 8142,
      "threat_activity": 0
    },
    "UA": {
      "exposed_services": 400798,
      "critical_vulns_estimate": 8015,
      "threat_activity": 0
    },
    "CO": {
      "exposed_services": 313708,
      "critical_vulns_estimate": 6274,
      "threat_activity": 0
    },
    "CL": {
      "exposed_services": 307227,
      "critical_vulns_estimate": 6144,
      "threat_activity": 0
    },
    "BG": {
      "exposed_services": 294594,
      "critical_vulns_estimate": 5891,
      "threat_activity": 0
    },
    "DK": {
      "exposed_services": 284002,
      "critical_vulns_estimate": 5680,
      "threat_activity": 0
    },
    "SA": {
      "exposed_services": 256585,
      "critical_vulns_estimate": 5131,
      "threat_activity": 0
    },
    "PH": {
      "exposed_services": 250524,
      "critical_vulns_estimate": 5010,
      "threat_activity": 0
    },
    "TN": {
      "exposed_services": 245676,
      "critical_vulns_estimate": 4913,
      "threat_activity": 0
    },
    "KZ": {
      "exposed_services": 235750,
      "critical_vulns_estimate": 4715,
      "threat_activity": 0
    },
    "HU": {
      "exposed_services": 224093,
      "critical_vulns_estimate": 4481,
      "threat_activity": 0
    },
    "EG": {
      "exposed_services": 205616,
      "critical_vulns_estimate": 4112,
      "threat_activity": 0
    },
    "NO": {
      "exposed_services": 193433,
      "critical_vulns_estimate": 3868,
      "threat_activity": 0
    }
  },
  "organizations": {
    "Amazon": {
      "exposed_services": 21855949,
      "critical_vulns_estimate": 327839
    },
    "Google": {
      "exposed_services": 6886794,
      "critical_vulns_estimate": 103301
    },
    "Microsoft": {
      "exposed_services": 7703872,
      "critical_vulns_estimate": 115558
    },
    "Cloudflare": {
      "exposed_services": 7434037,
      "critical_vulns_estimate": 111510
    },
    "DigitalOcean": {
      "exposed_services": 6347069,
      "critical_vulns_estimate": 95206
    }
  },
  "global_stats": {
    "total_exposed_services": 118314084,
    "total_critical_vulns": 2366259,
    "total_threat_activity": 15508,
    "malicious_domains": 0,
    "suspicious_domains": 1
  },
  "api_status": {
    "shodan": "active",
    "greynoise": "active",
    "virustotal": "active"
  }
}