{
  "timestamp": "2025-11-12T16:59:50.784865",
  "last_updated": "2025-11-12 16:59:50 UTC",
  "data_sources": [
    "Shodan Pro",
    "GreyNoise",
    "VirusTotal"
  ],
  "countries": {
    "US": {
      "exposed_services": 43090205,
      "critical_vulns": 861804,
      "threat_activity": 2065
    },
    "DE": {
      "exposed_services": 9979773,
      "critical_vulns": 199595,
      "threat_activity": 1373
    },
    "CN": {
      "exposed_services": 9801469,
      "critical_vulns": 196029,
      "threat_activity": 1953
    },
    "JP": {
      "exposed_services": 5129467,
      "critical_vulns": 102589,
      "threat_activity": 1840
    },
    "HK": {
      "exposed_services": 4304061,
      "critical_vulns": 86081,
      "threat_activity": 0
    },
    "GB": {
      "exposed_services": 3888748,
      "critical_vulns": 77774,
      "threat_activity": 2110
    },
    "IN": {
      "exposed_services": 3571649,
      "critical_vulns": 71432,
      "threat_activity": 0
    },
    "FR": {
      "exposed_services": 3398350,
      "critical_vulns": 67967,
      "threat_activity": 1706
    },
    "SG": {
      "exposed_services": 3395438,
      "critical_vulns": 67908,
      "threat_activity": 0
    },
    "NL": {
      "exposed_services": 3375321,
      "critical_vulns": 67506,
      "threat_activity": 0
    },
    "RU": {
      "exposed_services": 2759590,
      "critical_vulns": 55191,
      "threat_activity": 2148
    },
    "BR": {
      "exposed_services": 2566061,
      "critical_vulns": 51321,
      "threat_activity": 0
    },
    "KR": {
      "exposed_services": 2540306,
      "critical_vulns": 50806,
      "threat_activity": 1610
    },
    "CA": {
      "exposed_services": 2239301,
      "critical_vulns": 44786,
      "threat_activity": 1588
    },
    "AU": {
      "exposed_services": 2071343,
      "critical_vulns": 41426,
      "threat_activity": 2367
    },
    "IE": {
      "exposed_services": 1976565,
      "critical_vulns": 39531,
      "threat_activity": 0
    },
    "IT": {
      "exposed_services": 1779764,
      "critical_vulns": 35595,
      "threat_activity": 0
    },
    "TW": {
      "exposed_services": 1394185,
      "critical_vulns": 27883,
      "threat_activity": 0
    },
    "VN": {
      "exposed_services": 1222148,
      "critical_vulns": 24442,
      "threat_activity": 0
    },
    "ES": {
      "exposed_services": 1084565,
      "critical_vulns": 21691,
      "threat_activity": 0
    },
    "SE": {
      "exposed_services": 1022501,
      "critical_vulns": 20450,
      "threat_activity": 0
    },
    "PL": {
      "exposed_services": 1012278,
      "critical_vulns": 20245,
      "threat_activity": 0
    },
    "FI": {
      "exposed_services": 932387,
      "critical_vulns": 18647,
      "threat_activity": 0
    },
    "ID": {
      "exposed_services": 897679,
      "critical_vulns": 17953,
      "threat_activity": 0
    },
    "MX": {
      "exposed_services": 866856,
      "critical_vulns": 17337,
      "threat_activity": 0
    },
    "TH": {
      "exposed_services": 765206,
      "critical_vulns": 15304,
      "threat_activity": 0
    },
    "TR": {
      "exposed_services": 693216,
      "critical_vulns": 13864,
      "threat_activity": 0
    },
    "VE": {
      "exposed_services": 641790,
      "critical_vulns": 12835,
      "threat_activity": 0
    },
    "CH": {
      "exposed_services": 632355,
      "critical_vulns": 12647,
      "threat_activity": 0
    },
    "ZA": {
      "exposed_services": 625425,
      "critical_vulns": 12508,
      "threat_activity": 0
    },
    "AR": {
      "exposed_services": 624764,
      "critical_vulns": 12495,
      "threat_activity": 0
    },
    "BE": {
      "exposed_services": 548679,
      "critical_vulns": 10973,
      "threat_activity": 0
    },
    "RO": {
      "exposed_services": 528242,
      "critical_vulns": 10564,
      "threat_activity": 0
    },
    "AT": {
      "exposed_services": 476710,
      "critical_vulns": 9534,
      "threat_activity": 0
    },
    "MY": {
      "exposed_services": 436092,
      "critical_vulns": 8721,
      "threat_activity": 0
    },
    "IL": {
      "exposed_services": 416591,
      "critical_vulns": 8331,
      "threat_activity": 0
    },
    "UA": {
      "exposed_services": 412813,
      "critical_vulns": 8256,
      "threat_activity": 0
    },
    "CZ": {
      "exposed_services": 404045,
      "critical_vulns": 8080,
      "threat_activity": 0
    },
    "AE": {
      "exposed_services": 364797,
      "critical_vulns": 7295,
      "threat_activity": 0
    },
    "TN": {
      "exposed_services": 361634,
      "critical_vulns": 7232,
      "threat_activity": 0
    },
    "CL": {
      "exposed_services": 346839,
      "critical_vulns": 6936,
      "threat_activity": 0
    },
    "CO": {
      "exposed_services": 337677,
      "critical_vulns": 6753,
      "threat_activity": 0
    },
    "KZ": {
      "exposed_services": 293314,
      "critical_vulns": 5866,
      "threat_activity": 0
    },
    "BG": {
      "exposed_services": 292446,
      "critical_vulns": 5848,
      "threat_activity": 0
    },
    "PH": {
      "exposed_services": 287085,
      "critical_vulns": 5741,
      "threat_activity": 0
    },
    "EG": {
      "exposed_services": 268368,
      "critical_vulns": 5367,
      "threat_activity": 0
    },
    "DK": {
      "exposed_services": 251141,
      "critical_vulns": 5022,
      "threat_activity": 0
    },
    "HU": {
      "exposed_services": 238436,
      "critical_vulns": 4768,
      "threat_activity": 0
    },
    "SA": {
      "exposed_services": 227322,
      "critical_vulns": 4546,
      "threat_activity": 0
    },
    "IR": {
      "exposed_services": 226301,
      "critical_vulns": 4526,
      "threat_activity": 0
    }
  },
  "organizations": {
    "Amazon": {
      "exposed_services": 20254997,
      "critical_vulns": 303824
    },
    "Google": {
      "exposed_services": 556093470,
      "critical_vulns": 8341402
    },
    "Microsoft": {
      "exposed_services": 7580445,
      "critical_vulns": 113706
    },
    "Cloudflare": {
      "exposed_services": 8359516,
      "critical_vulns": 125392
    },
    "DigitalOcean": {
      "exposed_services": 7810470,
      "critical_vulns": 117157
    }
  },
  "global_stats": {
    "total_exposed_services": 125001298,
    "total_critical_vulns": 2500001,
    "total_threat_activity": 18760,
    "malicious_domains": 0,
    "suspicious_domains": 0
  },
  "api_status": {
    "shodan": "active",
    "greynoise": "active",
    "virustotal": "active"
  }
}