{
  "timestamp": "2025-08-09T22:46:02.644654",
  "last_updated": "2025-08-09 22:46:02 UTC",
  "data_sources": [
    "Shodan Pro",
    "GreyNoise",
    "VirusTotal"
  ],
  "countries": {
    "CN": {
      "exposed_services": 101290241,
      "critical_vulns": 2025804,
      "threat_activity": 1970
    },
    "US": {
      "exposed_services": 46940170,
      "critical_vulns": 938803,
      "threat_activity": 1676
    },
    "DE": {
      "exposed_services": 9975399,
      "critical_vulns": 199507,
      "threat_activity": 1600
    },
    "IN": {
      "exposed_services": 6448257,
      "critical_vulns": 128965,
      "threat_activity": 0
    },
    "JP": {
      "exposed_services": 4965754,
      "critical_vulns": 99315,
      "threat_activity": 1464
    },
    "RU": {
      "exposed_services": 4724556,
      "critical_vulns": 94491,
      "threat_activity": 1920
    },
    "HK": {
      "exposed_services": 4295728,
      "critical_vulns": 85914,
      "threat_activity": 0
    },
    "GB": {
      "exposed_services": 3742976,
      "critical_vulns": 74859,
      "threat_activity": 874
    },
    "NL": {
      "exposed_services": 3432433,
      "critical_vulns": 68648,
      "threat_activity": 0
    },
    "FR": {
      "exposed_services": 3391722,
      "critical_vulns": 67834,
      "threat_activity": 1512
    },
    "SG": {
      "exposed_services": 3340115,
      "critical_vulns": 66802,
      "threat_activity": 0
    },
    "BR": {
      "exposed_services": 3017112,
      "critical_vulns": 60342,
      "threat_activity": 0
    },
    "KR": {
      "exposed_services": 2461496,
      "critical_vulns": 49229,
      "threat_activity": 1634
    },
    "CA": {
      "exposed_services": 2182453,
      "critical_vulns": 43649,
      "threat_activity": 2056
    },
    "AU": {
      "exposed_services": 1957576,
      "critical_vulns": 39151,
      "threat_activity": 1177
    },
    "IT": {
      "exposed_services": 1817298,
      "critical_vulns": 36345,
      "threat_activity": 0
    },
    "IE": {
      "exposed_services": 1721022,
      "critical_vulns": 34420,
      "threat_activity": 0
    },
    "TW": {
      "exposed_services": 1498353,
      "critical_vulns": 29967,
      "threat_activity": 0
    },
    "VN": {
      "exposed_services": 1319990,
      "critical_vulns": 26399,
      "threat_activity": 0
    },
    "PL": {
      "exposed_services": 1119978,
      "critical_vulns": 22399,
      "threat_activity": 0
    },
    "ES": {
      "exposed_services": 1091256,
      "critical_vulns": 21825,
      "threat_activity": 0
    },
    "SE": {
      "exposed_services": 1016725,
      "critical_vulns": 20334,
      "threat_activity": 0
    },
    "FI": {
      "exposed_services": 926245,
      "critical_vulns": 18524,
      "threat_activity": 0
    },
    "ID": {
      "exposed_services": 903221,
      "critical_vulns": 18064,
      "threat_activity": 0
    },
    "MX": {
      "exposed_services": 894239,
      "critical_vulns": 17884,
      "threat_activity": 0
    },
    "TH": {
      "exposed_services": 797379,
      "critical_vulns": 15947,
      "threat_activity": 0
    },
    "VE": {
      "exposed_services": 773650,
      "critical_vulns": 15473,
      "threat_activity": 0
    },
    "CH": {
      "exposed_services": 716252,
      "critical_vulns": 14325,
      "threat_activity": 0
    },
    "TR": {
      "exposed_services": 703080,
      "critical_vulns": 14061,
      "threat_activity": 0
    },
    "AR": {
      "exposed_services": 685564,
      "critical_vulns": 13711,
      "threat_activity": 0
    },
    "ZA": {
      "exposed_services": 638965,
      "critical_vulns": 12779,
      "threat_activity": 0
    },
    "BE": {
      "exposed_services": 575384,
      "critical_vulns": 11507,
      "threat_activity": 0
    },
    "AT": {
      "exposed_services": 554475,
      "critical_vulns": 11089,
      "threat_activity": 0
    },
    "RO": {
      "exposed_services": 538661,
      "critical_vulns": 10773,
      "threat_activity": 0
    },
    "IR": {
      "exposed_services": 499997,
      "critical_vulns": 9999,
      "threat_activity": 0
    },
    "MY": {
      "exposed_services": 458269,
      "critical_vulns": 9165,
      "threat_activity": 0
    },
    "IL": {
      "exposed_services": 424586,
      "critical_vulns": 8491,
      "threat_activity": 0
    },
    "CZ": {
      "exposed_services": 412516,
      "critical_vulns": 8250,
      "threat_activity": 0
    },
    "UA": {
      "exposed_services": 402115,
      "critical_vulns": 8042,
      "threat_activity": 0
    },
    "TN": {
      "exposed_services": 379648,
      "critical_vulns": 7592,
      "threat_activity": 0
    },
    "CO": {
      "exposed_services": 365109,
      "critical_vulns": 7302,
      "threat_activity": 0
    },
    "CL": {
      "exposed_services": 357902,
      "critical_vulns": 7158,
      "threat_activity": 0
    },
    "DO": {
      "exposed_services": 357365,
      "critical_vulns": 7147,
      "threat_activity": 0
    },
    "KZ": {
      "exposed_services": 316091,
      "critical_vulns": 6321,
      "threat_activity": 0
    },
    "BG": {
      "exposed_services": 300620,
      "critical_vulns": 6012,
      "threat_activity": 0
    },
    "PH": {
      "exposed_services": 295213,
      "critical_vulns": 5904,
      "threat_activity": 0
    },
    "AE": {
      "exposed_services": 277537,
      "critical_vulns": 5550,
      "threat_activity": 0
    },
    "EG": {
      "exposed_services": 260034,
      "critical_vulns": 5200,
      "threat_activity": 0
    },
    "DK": {
      "exposed_services": 252945,
      "critical_vulns": 5058,
      "threat_activity": 0
    },
    "HU": {
      "exposed_services": 251346,
      "critical_vulns": 5026,
      "threat_activity": 0
    }
  },
  "organizations": {
    "Amazon": {
      "exposed_services": 18309607,
      "critical_vulns": 274644
    },
    "Google": {
      "exposed_services": 577934968,
      "critical_vulns": 8669024
    },
    "Microsoft": {
      "exposed_services": 7348833,
      "critical_vulns": 110232
    },
    "Cloudflare": {
      "exposed_services": 7832903,
      "critical_vulns": 117493
    },
    "DigitalOcean": {
      "exposed_services": 7850518,
      "critical_vulns": 117757
    }
  },
  "global_stats": {
    "total_exposed_services": 226069018,
    "total_critical_vulns": 4521356,
    "total_threat_activity": 15883,
    "malicious_domains": 0,
    "suspicious_domains": 0
  },
  "api_status": {
    "shodan": "active",
    "greynoise": "active",
    "virustotal": "active"
  }
}