{
  "timestamp": "2026-02-26T19:56:08.736682",
  "last_updated": "2026-02-26 19:56:08 UTC",
  "data_sources": [
    "Shodan Pro",
    "GreyNoise",
    "VirusTotal"
  ],
  "countries": {
    "US": {
      "exposed_services": 40353049,
      "critical_vulns": 807060,
      "threat_activity": 1397
    },
    "DE": {
      "exposed_services": 9674354,
      "critical_vulns": 193487,
      "threat_activity": 2113
    },
    "CN": {
      "exposed_services": 9277525,
      "critical_vulns": 185550,
      "threat_activity": 1176
    },
    "JP": {
      "exposed_services": 4928439,
      "critical_vulns": 98568,
      "threat_activity": 2384
    },
    "HK": {
      "exposed_services": 3913667,
      "critical_vulns": 78273,
      "threat_activity": 0
    },
    "GB": {
      "exposed_services": 3686900,
      "critical_vulns": 73738,
      "threat_activity": 831
    },
    "IN": {
      "exposed_services": 3398340,
      "critical_vulns": 67966,
      "threat_activity": 0
    },
    "SG": {
      "exposed_services": 3383267,
      "critical_vulns": 67665,
      "threat_activity": 0
    },
    "FR": {
      "exposed_services": 3312939,
      "critical_vulns": 66258,
      "threat_activity": 1128
    },
    "NL": {
      "exposed_services": 3199438,
      "critical_vulns": 63988,
      "threat_activity": 0
    },
    "BR": {
      "exposed_services": 2405688,
      "critical_vulns": 48113,
      "threat_activity": 0
    },
    "KR": {
      "exposed_services": 2392654,
      "critical_vulns": 47853,
      "threat_activity": 2379
    },
    "CA": {
      "exposed_services": 2135758,
      "critical_vulns": 42715,
      "threat_activity": 1562
    },
    "IE": {
      "exposed_services": 2081854,
      "critical_vulns": 41637,
      "threat_activity": 0
    },
    "AU": {
      "exposed_services": 2017195,
      "critical_vulns": 40343,
      "threat_activity": 1055
    },
    "RU": {
      "exposed_services": 1801077,
      "critical_vulns": 36021,
      "threat_activity": 1418
    },
    "IT": {
      "exposed_services": 1635998,
      "critical_vulns": 32719,
      "threat_activity": 0
    },
    "TW": {
      "exposed_services": 1278983,
      "critical_vulns": 25579,
      "threat_activity": 0
    },
    "VN": {
      "exposed_services": 1063594,
      "critical_vulns": 21271,
      "threat_activity": 0
    },
    "ES": {
      "exposed_services": 1045566,
      "critical_vulns": 20911,
      "threat_activity": 0
    },
    "SE": {
      "exposed_services": 989872,
      "critical_vulns": 19797,
      "threat_activity": 0
    },
    "FI": {
      "exposed_services": 950464,
      "critical_vulns": 19009,
      "threat_activity": 0
    },
    "PL": {
      "exposed_services": 910358,
      "critical_vulns": 18207,
      "threat_activity": 0
    },
    "ID": {
      "exposed_services": 874692,
      "critical_vulns": 17493,
      "threat_activity": 0
    },
    "MX": {
      "exposed_services": 782580,
      "critical_vulns": 15651,
      "threat_activity": 0
    },
    "TH": {
      "exposed_services": 680793,
      "critical_vulns": 13615,
      "threat_activity": 0
    },
    "TR": {
      "exposed_services": 645138,
      "critical_vulns": 12902,
      "threat_activity": 0
    },
    "CH": {
      "exposed_services": 636286,
      "critical_vulns": 12725,
      "threat_activity": 0
    },
    "ZA": {
      "exposed_services": 598767,
      "critical_vulns": 11975,
      "threat_activity": 0
    },
    "AR": {
      "exposed_services": 538890,
      "critical_vulns": 10777,
      "threat_activity": 0
    },
    "BE": {
      "exposed_services": 508330,
      "critical_vulns": 10166,
      "threat_activity": 0
    },
    "AE": {
      "exposed_services": 506014,
      "critical_vulns": 10120,
      "threat_activity": 0
    },
    "RO": {
      "exposed_services": 496203,
      "critical_vulns": 9924,
      "threat_activity": 0
    },
    "VE": {
      "exposed_services": 488401,
      "critical_vulns": 9768,
      "threat_activity": 0
    },
    "AT": {
      "exposed_services": 454525,
      "critical_vulns": 9090,
      "threat_activity": 0
    },
    "IR": {
      "exposed_services": 432991,
      "critical_vulns": 8659,
      "threat_activity": 0
    },
    "MY": {
      "exposed_services": 421096,
      "critical_vulns": 8421,
      "threat_activity": 0
    },
    "IL": {
      "exposed_services": 397549,
      "critical_vulns": 7950,
      "threat_activity": 0
    },
    "UA": {
      "exposed_services": 394464,
      "critical_vulns": 7889,
      "threat_activity": 0
    },
    "CZ": {
      "exposed_services": 392973,
      "critical_vulns": 7859,
      "threat_activity": 0
    },
    "CO": {
      "exposed_services": 315018,
      "critical_vulns": 6300,
      "threat_activity": 0
    },
    "BG": {
      "exposed_services": 290125,
      "critical_vulns": 5802,
      "threat_activity": 0
    },
    "CL": {
      "exposed_services": 285375,
      "critical_vulns": 5707,
      "threat_activity": 0
    },
    "DK": {
      "exposed_services": 282472,
      "critical_vulns": 5649,
      "threat_activity": 0
    },
    "PH": {
      "exposed_services": 274819,
      "critical_vulns": 5496,
      "threat_activity": 0
    },
    "TN": {
      "exposed_services": 270713,
      "critical_vulns": 5414,
      "threat_activity": 0
    },
    "SA": {
      "exposed_services": 246663,
      "critical_vulns": 4933,
      "threat_activity": 0
    },
    "KZ": {
      "exposed_services": 232702,
      "critical_vulns": 4654,
      "threat_activity": 0
    },
    "HU": {
      "exposed_services": 220564,
      "critical_vulns": 4411,
      "threat_activity": 0
    },
    "EG": {
      "exposed_services": 213589,
      "critical_vulns": 4271,
      "threat_activity": 0
    }
  },
  "organizations": {
    "Amazon": {
      "exposed_services": 21198385,
      "critical_vulns": 317975
    },
    "Google": {
      "exposed_services": 6707863,
      "critical_vulns": 100617
    },
    "Microsoft": {
      "exposed_services": 6926682,
      "critical_vulns": 103900
    },
    "Cloudflare": {
      "exposed_services": 7460824,
      "critical_vulns": 111912
    },
    "DigitalOcean": {
      "exposed_services": 6224974,
      "critical_vulns": 93374
    }
  },
  "global_stats": {
    "total_exposed_services": 117718711,
    "total_critical_vulns": 2354349,
    "total_threat_activity": 15443,
    "malicious_domains": 0,
    "suspicious_domains": 0
  },
  "api_status": {
    "shodan": "active",
    "greynoise": "active",
    "virustotal": "active"
  }
}